paig_client/PluginAccessRequestEncryptor.py
paig_client/VERSION
paig_client/__init__.py
paig_client/backend.py
paig_client/client.py
paig_client/core.py
paig_client/encryption.py
paig_client/exception.py
paig_client/interceptor.py
paig_client/interceptor_setup.py
paig_client/langchain_callback.py
paig_client/langchain_method_interceptor.py
paig_client/langchain_streaming_interceptor.py
paig_client/message.py
paig_client/milvus_method_interceptor.py
paig_client/model.py
paig_client/opensearch_method_interceptor.py
paig_client/util.py
paig_client/posthog_events/__init__.py
paig_client/posthog_events/events.py
paig_client/posthog_events/metric_collector.py
paig_client/posthog_events/posthog.py
paig_client-0.0.6.dist-info/METADATA
paig_client-0.0.6.dist-info/WHEEL
paig_client-0.0.6.dist-info/RECORD
