Metadata-Version: 2.4
Name: paig-client
Version: 0.0.6
Summary: PAIG Shield Client Library
Project-URL: Homepage, https://github.com/pypa/paig_client
Project-URL: Bug Tracker, https://github.com/pypa/paig_client/issues
Author-email: Privacera  <support@privacera.com>
License:                                  Apache License
Classifier: License :: Other/Proprietary License
Classifier: Operating System :: OS Independent
Classifier: Programming Language :: Python :: 3
Requires-Python: >=3.8.1
Requires-Dist: cryptography>=41.0.4
Requires-Dist: paig-common
Requires-Dist: posthog
Requires-Dist: urllib3>=2.0.6
